cosmotech/coal/__init__.py
cosmotech/coal/aws/__init__.py
cosmotech/coal/aws/s3.py
cosmotech/coal/azure/__init__.py
cosmotech/coal/azure/blob.py
cosmotech/coal/azure/functions.py
cosmotech/coal/azure/storage.py
cosmotech/coal/azure/adx/__init__.py
cosmotech/coal/azure/adx/auth.py
cosmotech/coal/azure/adx/ingestion.py
cosmotech/coal/azure/adx/query.py
cosmotech/coal/azure/adx/runner.py
cosmotech/coal/azure/adx/store.py
cosmotech/coal/azure/adx/tables.py
cosmotech/coal/azure/adx/utils.py
cosmotech/coal/cosmotech_api/__init__.py
cosmotech/coal/cosmotech_api/connection.py
cosmotech/coal/cosmotech_api/parameters.py
cosmotech/coal/cosmotech_api/run.py
cosmotech/coal/cosmotech_api/run_data.py
cosmotech/coal/cosmotech_api/run_template.py
cosmotech/coal/cosmotech_api/twin_data_layer.py
cosmotech/coal/cosmotech_api/workspace.py
cosmotech/coal/cosmotech_api/dataset/__init__.py
cosmotech/coal/cosmotech_api/dataset/converters.py
cosmotech/coal/cosmotech_api/dataset/upload.py
cosmotech/coal/cosmotech_api/dataset/utils.py
cosmotech/coal/cosmotech_api/dataset/download/__init__.py
cosmotech/coal/cosmotech_api/dataset/download/adt.py
cosmotech/coal/cosmotech_api/dataset/download/common.py
cosmotech/coal/cosmotech_api/dataset/download/file.py
cosmotech/coal/cosmotech_api/dataset/download/twingraph.py
cosmotech/coal/cosmotech_api/runner/__init__.py
cosmotech/coal/cosmotech_api/runner/data.py
cosmotech/coal/cosmotech_api/runner/datasets.py
cosmotech/coal/cosmotech_api/runner/download.py
cosmotech/coal/cosmotech_api/runner/metadata.py
cosmotech/coal/cosmotech_api/runner/parameters.py
cosmotech/coal/csm/__init__.py
cosmotech/coal/csm/engine/__init__.py
cosmotech/coal/postgresql/__init__.py
cosmotech/coal/postgresql/runner.py
cosmotech/coal/postgresql/store.py
cosmotech/coal/singlestore/__init__.py
cosmotech/coal/singlestore/store.py
cosmotech/coal/store/__init__.py
cosmotech/coal/store/csv.py
cosmotech/coal/store/native_python.py
cosmotech/coal/store/pandas.py
cosmotech_acceleration_library-1.1.0.dist-info/licenses/LICENSE
cosmotech_acceleration_library-1.1.0.dist-info/METADATA
cosmotech_acceleration_library-1.1.0.dist-info/WHEEL
cosmotech_acceleration_library-1.1.0.dist-info/entry_points.txt
cosmotech_acceleration_library-1.1.0.dist-info/top_level.txt
cosmotech_acceleration_library-1.1.0.dist-info/RECORD
