Metadata-Version: 2.4
Name: cosmotech_acceleration_library
Version: 1.1.0
Summary: Acceleration libraries for CosmoTech cloud based solution development
Author-email: Cosmo Tech <platform@cosmotech.com>
Project-URL: Homepage, https://www.cosmotech.com
Project-URL: Source, https://github.com/Cosmo-Tech/CosmoTech-Acceleration-Library
Project-URL: Documentation, https://cosmo-tech.github.io/CosmoTech-Acceleration-Library
License-File: LICENSE
Requires-Dist: azure-functions~=1.20.0
Requires-Dist: azure-digitaltwins-core~=1.2.0
Requires-Dist: azure-identity~=1.16.1
Requires-Dist: azure-kusto-data~=4.4.1
Requires-Dist: azure-kusto-ingest~=4.4.1
Requires-Dist: tenacity~=8.3.0
Requires-Dist: python-keycloak~=4.7.3
Requires-Dist: cosmotech-api>=3.2
Requires-Dist: boto3~=1.35.19
Requires-Dist: requests~=2.32.3
Requires-Dist: singlestoredb~=1.10.0
Requires-Dist: cosmotech-run-orchestrator~=2.0.0
Requires-Dist: pyarrow~=20.0.0
Requires-Dist: adbc-driver-manager~=1.7.0
Requires-Dist: adbc-driver-sqlite~=1.7.0
Requires-Dist: adbc-driver-postgresql~=1.7.0
Requires-Dist: click~=8.1.7
Requires-Dist: rich-click~=1.7.3
Requires-Dist: click-log~=0.4.0
Requires-Dist: tqdm~=4.67.1
Requires-Dist: openpyxl~=3.1
Requires-Dist: pandas~=2.1
Requires-Dist: python-dateutil~=2.8
Requires-Dist: rich~=13.7
Requires-Dist: setuptools
Provides-Extra: doc
Requires-Dist: mkdocs~=1.6.1; extra == "doc"
Requires-Dist: mkdocs-click~=0.8.1; extra == "doc"
Requires-Dist: mkdocs-gen-files~=0.5.0; extra == "doc"
Requires-Dist: mkdocstrings[python]~=0.28.2; extra == "doc"
Requires-Dist: mkdocs-awesome-nav~=3.1.2; extra == "doc"
Requires-Dist: pymdown-extensions~=10.7; extra == "doc"
Requires-Dist: requirements-parser~=0.11.0; extra == "doc"
Requires-Dist: mike~=2.0.0; extra == "doc"
Requires-Dist: griffe~=1.5.7; extra == "doc"
Requires-Dist: mkdocs-include-dir-to-nav~=1.2.0; extra == "doc"
Requires-Dist: mkdocs-material[imaging]~=9.6.14; extra == "doc"
Requires-Dist: mkdocs-table-reader-plugin~=2.0.3; extra == "doc"
Requires-Dist: mkdocs-literate-nav~=0.6.1; extra == "doc"
Provides-Extra: test
Requires-Dist: pytest; extra == "test"
Requires-Dist: pytest-docker; extra == "test"
Requires-Dist: pytest-cov; extra == "test"
Provides-Extra: extra
Requires-Dist: pandas~=2.2.2; extra == "extra"
Provides-Extra: dev
Requires-Dist: black~=24.3.0; extra == "dev"
Requires-Dist: pre-commit~=3.3.2; extra == "dev"
Provides-Extra: all
Requires-Dist: CosmoTech_Acceleration_Library[dev,doc,extra,test]; extra == "all"
Provides-Extra: past
Requires-Dist: cosmotech-api~=3.2; extra == "past"
Dynamic: license-file
